{
  "key": "pf_feed_queue",
  "value": "[{\"id\":\"feed_001\",\"company\":\"TechFlow Inc\",\"title\":\"Senior Product Manager - AI Platform\",\"url\":\"https://example.com/jobs/techflow-pm-ai\",\"location\":\"San Francisco, CA\",\"source\":\"LinkedIn\",\"emailDate\":\"2026-04-05T08:30:00.000Z\",\"addedAt\":\"2026-04-05T09:15:00.000Z\",\"companyStage\":\"Series C+\",\"score\":92,\"scoring\":{\"titleFit\":95,\"domainFit\":98,\"levelFit\":92,\"locationFit\":100},\"reasons\":[\"AI/ML domain match\",\"Senior level\",\"Series C+ company\",\"SF location\"],\"hasFullJD\":true,\"compensation\":\"$260K - $310K + 0.3-0.5% equity\",\"status\":\"bookmarked\"},{\"id\":\"feed_002\",\"company\":\"Nexus AI\",\"title\":\"Senior Product Manager - ML Ops\",\"url\":\"https://example.com/jobs/nexus-pm-mlops\",\"location\":\"Seattle, WA\",\"source\":\"LinkedIn\",\"emailDate\":\"2026-04-04T14:00:00.000Z\",\"addedAt\":\"2026-04-04T14:45:00.000Z\",\"companyStage\":\"Series C+\",\"score\":90,\"scoring\":{\"titleFit\":94,\"domainFit\":96,\"levelFit\":90,\"locationFit\":90},\"reasons\":[\"AI/ML focus\",\"Machine learning\",\"Platform strategy\",\"Seattle tech hub\"],\"hasFullJD\":true,\"compensation\":\"$255K - $305K + 0.35-0.55% equity\",\"status\":\"null\"},{\"id\":\"feed_003\",\"company\":\"CloudNine Systems\",\"title\":\"Senior Product Manager - Infrastructure\",\"url\":\"https://example.com/jobs/cloudnine-pm\",\"location\":\"Remote\",\"source\":\"AngelList\",\"emailDate\":\"2026-04-03T10:20:00.000Z\",\"addedAt\":\"2026-04-03T11:00:00.000Z\",\"companyStage\":\"Series B\",\"score\":88,\"scoring\":{\"titleFit\":92,\"domainFit\":95,\"levelFit\":88,\"locationFit\":100},\"reasons\":[\"Cloud Infrastructure\",\"Developer Tools adjacent\",\"Remote\",\"Cross-functional team\"],\"hasFullJD\":true,\"compensation\":\"$240K - $290K + 0.25-0.4% equity\",\"status\":\"null\"},{\"id\":\"feed_004\",\"company\":\"DataVault\",\"title\":\"Director of Product - Data Platform\",\"url\":\"https://example.com/jobs/datavault-director\",\"location\":\"New York, NY\",\"source\":\"Insider\",\"emailDate\":\"2026-04-02T16:30:00.000Z\",\"addedAt\":\"2026-04-02T17:15:00.000Z\",\"companyStage\":\"Series B\",\"score\":85,\"scoring\":{\"titleFit\":98,\"domainFit\":88,\"levelFit\":95,\"locationFit\":95},\"reasons\":[\"Director level\",\"Data platform\",\"East coast\",\"Strategy focus\"],\"hasFullJD\":false,\"compensation\":\"$270K - $330K + 0.4-0.6% equity\",\"status\":\"bookmarked\"},{\"id\":\"feed_005\",\"company\":\"Acme Corp\",\"title\":\"Principal Product Manager - Growth\",\"url\":\"https://example.com/jobs/acme-principal-growth\",\"location\":\"Austin, TX\",\"source\":\"Company Career Page\",\"emailDate\":\"2026-04-01T12:00:00.000Z\",\"addedAt\":\"2026-04-01T13:00:00.000Z\",\"companyStage\":\"Late-stage / Pre-IPO\",\"score\":79,\"scoring\":{\"titleFit\":88,\"domainFit\":72,\"levelFit\":92,\"locationFit\":85},\"reasons\":[\"Principal level\",\"Growth keyword\",\"Pre-IPO\",\"Austin location\"],\"hasFullJD\":true,\"compensation\":\"$290K - $360K + 0.5-0.8% equity\",\"status\":\"null\"},{\"id\":\"feed_006\",\"company\":\"TechFlow Inc\",\"title\":\"Staff Product Manager - Developer Experience\",\"url\":\"https://example.com/jobs/techflow-staff-dx\",\"location\":\"San Francisco, CA\",\"source\":\"LinkedIn\",\"emailDate\":\"2026-03-31T09:45:00.000Z\",\"addedAt\":\"2026-03-31T10:30:00.000Z\",\"companyStage\":\"Series C+\",\"score\":87,\"scoring\":{\"titleFit\":93,\"domainFit\":96,\"levelFit\":89,\"locationFit\":100},\"reasons\":[\"Developer Tools domain\",\"Staff level\",\"DX focus\",\"SF location\"],\"hasFullJD\":true,\"compensation\":\"$275K - $330K + 0.4-0.6% equity\",\"status\":\"null\"},{\"id\":\"feed_007\",\"company\":\"CloudNine Systems\",\"title\":\"Senior Product Manager - Platform\",\"url\":\"https://example.com/jobs/cloudnine-platform\",\"location\":\"Remote\",\"source\":\"LinkedIn\",\"emailDate\":\"2026-03-29T14:15:00.000Z\",\"addedAt\":\"2026-03-29T15:00:00.000Z\",\"companyStage\":\"Series B\",\"score\":83,\"scoring\":{\"titleFit\":90,\"domainFit\":92,\"levelFit\":85,\"locationFit\":100},\"reasons\":[\"Platform keyword\",\"Cloud Infrastructure\",\"Remote option\",\"Series B growth\"],\"hasFullJD\":false,\"compensation\":\"$235K - $285K + 0.25-0.4% equity\",\"status\":\"null\"},{\"id\":\"feed_008\",\"company\":\"Nexus AI\",\"title\":\"Director of Product Strategy\",\"url\":\"https://example.com/jobs/nexus-director-strategy\",\"location\":\"Seattle, WA\",\"source\":\"AngelList\",\"emailDate\":\"2026-03-27T11:30:00.000Z\",\"addedAt\":\"2026-03-27T12:15:00.000Z\",\"companyStage\":\"Series C+\",\"score\":86,\"scoring\":{\"titleFit\":96,\"domainFit\":94,\"levelFit\":93,\"locationFit\":90},\"reasons\":[\"Director level\",\"Strategy focus\",\"AI/ML company\",\"Roadmap experience\"],\"hasFullJD\":true,\"compensation\":\"$280K - $350K + 0.45-0.7% equity\",\"status\":\"null\"},{\"id\":\"feed_009\",\"company\":\"DataVault\",\"title\":\"Senior Product Manager - ML Infrastructure\",\"url\":\"https://example.com/jobs/datavault-pm-mlinfra\",\"location\":\"New York, NY\",\"source\":\"Insider\",\"emailDate\":\"2026-03-25T13:00:00.000Z\",\"addedAt\":\"2026-03-25T13:45:00.000Z\",\"companyStage\":\"Series B\",\"score\":81,\"scoring\":{\"titleFit\":91,\"domainFit\":89,\"levelFit\":87,\"locationFit\":92},\"reasons\":[\"ML Infrastructure\",\"Data platform\",\"Machine learning boost\",\"East coast\"],\"hasFullJD\":false,\"compensation\":\"$245K - $295K + 0.3-0.45% equity\",\"status\":\"null\"},{\"id\":\"feed_010\",\"company\":\"Acme Corp\",\"title\":\"Senior Product Manager - SaaS Platform\",\"url\":\"https://example.com/jobs/acme-saas-pm\",\"location\":\"Austin, TX\",\"source\":\"Company Career Page\",\"emailDate\":\"2026-03-22T10:00:00.000Z\",\"addedAt\":\"2026-03-22T10:45:00.000Z\",\"companyStage\":\"Late-stage / Pre-IPO\",\"score\":76,\"scoring\":{\"titleFit\":85,\"domainFit\":68,\"levelFit\":84,\"locationFit\":85},\"reasons\":[\"Senior PM\",\"SaaS domain\",\"Pre-IPO company\",\"Austin location\"],\"hasFullJD\":true,\"compensation\":\"$250K - $300K + 0.35-0.5% equity\",\"status\":\"null\"}]",
  "updatedAt": "2026-04-05T18:00:00.000Z",
  "sizeBytes": 4891
}
